Metadata-Version: 2.1
Name: jobs-scraper
Version: 0.0.11
Summary: A simple job postings scraper for Indeed based on requests and BeautifulSoup.
Home-page: https://github.com/vittoriotriassi/jobs_scraper
Author: Vittorio Triassi
Author-email: vi.triassi@gmail.com
License: MIT
Platform: UNKNOWN
Classifier: Development Status :: 3 - Alpha
Classifier: Intended Audience :: Education
Classifier: License :: OSI Approved :: MIT License
Classifier: Programming Language :: Python :: 3
Provides-Extra: test
License-File: LICENSE
